arango/__init__.py
arango/api.py
arango/aql.py
arango/backup.py
arango/client.py
arango/cluster.py
arango/collection.py
arango/connection.py
arango/cursor.py
arango/database.py
arango/errno.py
arango/exceptions.py
arango/executor.py
arango/formatter.py
arango/foxx.py
arango/graph.py
arango/http.py
arango/job.py
arango/pregel.py
arango/py.typed
arango/replication.py
arango/request.py
arango/resolver.py
arango/response.py
arango/result.py
arango/typings.py
arango/utils.py
arango/version.py
arango/wal.py
python_arango-8.2.6.dist-info/licenses/LICENSE
python_arango-8.2.6.dist-info/METADATA
python_arango-8.2.6.dist-info/WHEEL
python_arango-8.2.6.dist-info/top_level.txt
python_arango-8.2.6.dist-info/RECORD
